README.md
setup.cfg
setup.py
celery_macrobase/__init__.py
celery_macrobase/config.py
celery_macrobase/driver.py
celery_macrobase/endpoint.py
celery_macrobase/exceptions.py
celery_macrobase/hook.py
celery_macrobase/method.py
celery_macrobase/schedule.py
celery_macrobase.egg-info/PKG-INFO
celery_macrobase.egg-info/SOURCES.txt
celery_macrobase.egg-info/dependency_links.txt
celery_macrobase.egg-info/requires.txt
celery_macrobase.egg-info/top_level.txt